canonicalwebteam/upload_assets/uploader.py
canonicalwebteam.upload_assets-0.4.1.data/scripts/upload-assets
canonicalwebteam.upload_assets-0.4.1.dist-info/METADATA
canonicalwebteam.upload_assets-0.4.1.dist-info/WHEEL
canonicalwebteam.upload_assets-0.4.1.dist-info/top_level.txt
canonicalwebteam.upload_assets-0.4.1.dist-info/RECORD
