Metadata-Version: 2.1
Name: canonicalwebteam.upload-assets
Version: 0.4.1
Summary: A command-line tool for uploading assets to an assets server.
Home-page: https://github.com/canonical-web-and-design/upload-assets
Author: Canonical webteam
Author-email: robin+pypi@canonical.com
Requires-Dist: requests >=2.13.0
